santorinai/__init__.py
santorinai/board.py
santorinai/pawn.py
santorinai/player.py
santorinai/tester.py
santorinai/board_displayer/__init__.py
santorinai/board_displayer/board_displayer.py
santorinai/player_examples/__init__.py
santorinai/player_examples/basic_player.py
santorinai/player_examples/first_choice_player.py
santorinai/player_examples/random_player.py
test/__init__.py
test/test_board.py
test/test_tester.py
SantorinAI-1.3.3.dist-info/LICENSE
SantorinAI-1.3.3.dist-info/METADATA
SantorinAI-1.3.3.dist-info/WHEEL
SantorinAI-1.3.3.dist-info/top_level.txt
SantorinAI-1.3.3.dist-info/RECORD
