Metadata-Version: 2.1
Name: SantorinAI
Version: 1.3.3
Summary: A Python library for the Santorini board game
Home-page: https://github.com/tomansion/santorinai
Author: Tom Mansion
Author-email: tomansion@yahoo.fr
Keywords: santorini,ai,boardgame
Classifier: License :: OSI Approved :: Apache Software License
Classifier: Programming Language :: Python
Classifier: Programming Language :: Python :: 3
Requires-Python: >=3.6
License-File: LICENSE
Requires-Dist: pysimplegui
